{
  "chunkX": -8,
  "chunkZ": 3,
  "records": [
    {
      "horizontalPos": 145,
      "y": 24,
      "blockId": 0
    },
    {
      "horizontalPos": 128,
      "y": 24,
      "blockId": 0
    },
    {
      "horizontalPos": 129,
      "y": 24,
      "blockId": 0
    },
    {
      "horizontalPos": 146,
      "y": 24,
      "blockId": 0
    },
    {
      "horizontalPos": 130,
      "y": 25,
      "blockId": 0
    },
    {
      "horizontalPos": 113,
      "y": 25,
      "blockId": 0
    },
    {
      "horizontalPos": 112,
      "y": 24,
      "blockId": 0
    }
  ]
}