{
  "entityId": 62,
  "properties": [
    {
      "key": "generic.maxHealth",
      "value": 20,
      "modifiers": []
    },
    {
      "key": "generic.movementSpeed",
      "value": 0.18629200794561265,
      "modifiers": []
    },
    {
      "key": "generic.armorToughness",
      "value": 0,
      "modifiers": []
    },
    {
      "key": "generic.armor",
      "value": 0,
      "modifiers": []
    },
    {
      "key": "horse.jumpStrength",
      "value": 0.7204835712852998,
      "modifiers": []
    }
  ]
}