{
  "location": {
    "x": 45,
    "y": 59,
    "z": -98
  },
  "action": 1,
  "nbtData": {
    "type": "compound",
    "name": "",
    "value": {
      "EntityId": {
        "type": "string",
        "value": "Zombie"
      },
      "MaxNearbyEntities": {
        "type": "short",
        "value": 6
      },
      "RequiredPlayerRange": {
        "type": "short",
        "value": 16
      },
      "SpawnCount": {
        "type": "short",
        "value": 4
      },
      "x": {
        "type": "int",
        "value": 45
      },
      "y": {
        "type": "int",
        "value": 59
      },
      "z": {
        "type": "int",
        "value": -98
      },
      "id": {
        "type": "string",
        "value": "MobSpawner"
      },
      "MaxSpawnDelay": {
        "type": "short",
        "value": 800
      },
      "SpawnRange": {
        "type": "short",
        "value": 4
      },
      "Delay": {
        "type": "short",
        "value": 20
      },
      "MinSpawnDelay": {
        "type": "short",
        "value": 200
      }
    }
  }
}